detach/__init__.py
detach3k-1.0.0.dist-info/LICENSE
detach3k-1.0.0.dist-info/WHEEL
detach3k-1.0.0.dist-info/METADATA
detach3k-1.0.0.dist-info/RECORD
