Metadata-Version: 2.1
Name: detach3k
Version: 1.0.0
Summary: Fork and detach the current process.
Home-page: https://github.com/reversefold/detach
License: BSD-derived
Keywords: fork,daemon,detach
Author: Julia Patrin
Author-email: papercrane@reversefold.com
Requires-Python: >=3.7,<4
Classifier: Intended Audience :: Developers
Classifier: License :: OSI Approved :: BSD License
Classifier: License :: Other/Proprietary License
Classifier: Programming Language :: Python
Classifier: Programming Language :: Python :: 3
Classifier: Programming Language :: Python :: 3.7
Classifier: Programming Language :: Python :: 3.8
Classifier: Programming Language :: Python :: 3.9
Project-URL: Repository, https://github.com/reversefold/detach.git
